VMNeuralNetwork/Activation_Functions.py
VMNeuralNetwork/Layer.py
VMNeuralNetwork/NN_framework.py
VMNeuralNetwork/__init__.py
VMNeuralNetwork-1.171.dist-info/METADATA
VMNeuralNetwork-1.171.dist-info/WHEEL
VMNeuralNetwork-1.171.dist-info/top_level.txt
VMNeuralNetwork-1.171.dist-info/RECORD
